dagster_msteams/__init__.py
dagster_msteams/card.py
dagster_msteams/client.py
dagster_msteams/hooks.py
dagster_msteams/resources.py
dagster_msteams/sensors.py
dagster_msteams/version.py
dagster_msteams-1.0.5.dist-info/LICENSE
dagster_msteams-1.0.5.dist-info/METADATA
dagster_msteams-1.0.5.dist-info/WHEEL
dagster_msteams-1.0.5.dist-info/top_level.txt
dagster_msteams-1.0.5.dist-info/RECORD
